tonaton.py
jumia/__init__.py
jumia/scraper.py
jumia/utils.py
tonaton/__init__.py
tonaton/scraper.py
tonaton/scrapy.py
tonaton/utils.py
ghanashops_scraper-0.0.11.dist-info/METADATA
ghanashops_scraper-0.0.11.dist-info/WHEEL
ghanashops_scraper-0.0.11.dist-info/top_level.txt
ghanashops_scraper-0.0.11.dist-info/RECORD
